guify/App.py
guify/BaseTest.py
guify/ConfigTab.py
guify/Monitor.py
guify/TestPool.py
guify/TestWorker.py
guify/__init__.py
guify/constants.py
guify/report_template.html
guify/utils.py
guify/web/asset-manifest.json
guify/web/favicon.ico
guify/web/index.html
guify/web/manifest.json
guify/web/static/css/main.1249f42c.css
guify/web/static/css/main.1249f42c.css.map
guify/web/static/js/main.19064993.js
guify/web/static/js/main.19064993.js.LICENSE.txt
guify/web/static/js/main.19064993.js.map
guify-0.3.2.dist-info/LICENSE
guify-0.3.2.dist-info/METADATA
guify-0.3.2.dist-info/WHEEL
guify-0.3.2.dist-info/top_level.txt
guify-0.3.2.dist-info/RECORD
