Metadata-Version: 2.1
Name: guify
Version: 0.3.2
Summary: A tool that will GUI-ify your functions
Author: Michael Druyan
Author-email: michael@druyan.net
Classifier: Programming Language :: Python :: 3
License-File: LICENSE
Requires-Dist: bottle (==0.12.25)
Requires-Dist: bottle-websocket (==0.2.9)
Requires-Dist: eel (==0.16.0)
Requires-Dist: gevent-websocket (==0.10.1)
Requires-Dist: pycparser (==2.21)
Requires-Dist: pymsgbox (==1.0.9)
Requires-Dist: whichcraft (==0.6.1)
Requires-Dist: zope.event (==4.6)
Requires-Dist: greenlet (==2.0.2) ; platform_python_implementation == "CPython"
Requires-Dist: cffi (==1.15.1) ; platform_python_implementation == "CPython" and sys_platform == "win32"
Requires-Dist: pyparsing (==3.0.9) ; python_full_version >= "3.6.8"
Requires-Dist: future (==0.18.3) ; python_version >= "2.6" and python_version not in "3.0, 3.1, 3.2, 3.3"
Requires-Dist: gevent (==22.10.2) ; python_version >= "2.7" and python_version not in "3.0, 3.1, 3.2, 3.3, 3.4, 3.5"
Requires-Dist: setuptools (==67.7.2) ; python_version >= "3.7"
Requires-Dist: zope.interface (==6.0) ; python_version >= "3.7"
